topsis/__init__.py
topsis/cli.py
topsis/topsis.py
topsis_cli-1.0.1.dist-info/METADATA
topsis_cli-1.0.1.dist-info/WHEEL
topsis_cli-1.0.1.dist-info/entry_points.txt
topsis_cli-1.0.1.dist-info/top_level.txt
topsis_cli-1.0.1.dist-info/RECORD
