Metadata-Version: 2.1
Name: topsis-cli
Version: 1.0.1
Summary: A CLI tool for TOPSIS decision-making
Home-page: https://github.com/nmnbabbar/topsis-cli
Author: Naman Babbar
Author-email: nbabbar_be22@thapar.edu
Classifier: Programming Language :: Python :: 3
Classifier: License :: OSI Approved :: MIT License
Classifier: Operating System :: OS Independent
Requires-Python: >=3.7
Requires-Dist: numpy
Requires-Dist: pandas
